jupyterhub/__init__.py
jupyterhub/__main__.py
jupyterhub/_data.py
jupyterhub/_memoize.py
jupyterhub/_version.py
jupyterhub/_xsrf_utils.py
jupyterhub/alembic.ini
jupyterhub/app.py
jupyterhub/auth.py
jupyterhub/crypto.py
jupyterhub/dbutil.py
jupyterhub/emptyclass.py
jupyterhub/log.py
jupyterhub/metrics.py
jupyterhub/objects.py
jupyterhub/orm.py
jupyterhub/proxy.py
jupyterhub/roles.py
jupyterhub/scopes.py
jupyterhub/spawner.py
jupyterhub/traitlets.py
jupyterhub/user.py
jupyterhub/utils.py
jupyterhub/alembic/README
jupyterhub/alembic/env.py
jupyterhub/alembic/script.py.mako
jupyterhub/alembic/versions/0eee8c825d24_added_properties_column.py
jupyterhub/alembic/versions/19c0846f6344_base_revision_for_0_5.py
jupyterhub/alembic/versions/1cebaf56856c_session_id.py
jupyterhub/alembic/versions/3ec6993fe20c_encrypted_auth_state.py
jupyterhub/alembic/versions/4dc2d5a8c53c_user_options.py
jupyterhub/alembic/versions/56cc5a70207e_token_tracking.py
jupyterhub/alembic/versions/651f5419b74d_api_token_scopes.py
jupyterhub/alembic/versions/833da8570507_rbac.py
jupyterhub/alembic/versions/896818069c98_token_expires.py
jupyterhub/alembic/versions/99a28a4418e1_user_created.py
jupyterhub/alembic/versions/af4cbdb2d13c_services.py
jupyterhub/alembic/versions/d68c98b66cd4_client_description.py
jupyterhub/alembic/versions/eeb276e51423_auth_state.py
jupyterhub/apihandlers/__init__.py
jupyterhub/apihandlers/auth.py
jupyterhub/apihandlers/base.py
jupyterhub/apihandlers/groups.py
jupyterhub/apihandlers/hub.py
jupyterhub/apihandlers/proxy.py
jupyterhub/apihandlers/services.py
jupyterhub/apihandlers/users.py
jupyterhub/event-schemas/server-actions/v1.yaml
jupyterhub/handlers/__init__.py
jupyterhub/handlers/base.py
jupyterhub/handlers/login.py
jupyterhub/handlers/metrics.py
jupyterhub/handlers/pages.py
jupyterhub/handlers/static.py
jupyterhub/oauth/__init__.py
jupyterhub/oauth/provider.py
jupyterhub/services/__init__.py
jupyterhub/services/auth.py
jupyterhub/services/service.py
jupyterhub-4.1.6.dist-info/COPYING.md
jupyterhub-4.1.6.dist-info/METADATA
jupyterhub-4.1.6.dist-info/WHEEL
jupyterhub-4.1.6.dist-info/entry_points.txt
jupyterhub-4.1.6.dist-info/top_level.txt
jupyterhub-4.1.6.dist-info/RECORD
