Metadata-Version: 2.1
Name: jupyterhub
Version: 4.1.6
Summary: JupyterHub: A multi-user server for Jupyter notebooks
Home-page: https://jupyter.org
Author: Jupyter Development Team
Author-email: jupyter@googlegroups.com
License: BSD
Project-URL: Documentation, https://jupyterhub.readthedocs.io
Project-URL: Funding, https://jupyter.org/about
Project-URL: Source, https://github.com/jupyterhub/jupyterhub/
Project-URL: Tracker, https://github.com/jupyterhub/jupyterhub/issues
Keywords: Interactive,Interpreter,Shell,Web
Platform: Linux
Platform: Mac OS X
Classifier: Intended Audience :: Developers
Classifier: Intended Audience :: System Administrators
Classifier: Intended Audience :: Science/Research
Classifier: License :: OSI Approved :: BSD License
Classifier: Programming Language :: Python
Classifier: Programming Language :: Python :: 3
Requires-Python: >=3.7
License-File: COPYING.md
Requires-Dist: alembic >=1.4
Requires-Dist: async-generator >=1.9
Requires-Dist: certipy >=0.1.2
Requires-Dist: jinja2 >=2.11.0
Requires-Dist: jupyter-telemetry >=0.1.0
Requires-Dist: oauthlib >=3.0
Requires-Dist: packaging
Requires-Dist: prometheus-client >=0.4.0
Requires-Dist: python-dateutil
Requires-Dist: requests
Requires-Dist: SQLAlchemy >=1.4
Requires-Dist: tornado >=5.1
Requires-Dist: traitlets >=4.3.2
Requires-Dist: importlib-metadata >=3.6 ; python_version < "3.10"
Requires-Dist: pamela ; sys_platform != "win32"
Requires-Dist: psutil >=5.6.5 ; sys_platform == "win32"
Provides-Extra: test
Requires-Dist: beautifulsoup4[html5lib] ; extra == 'test'
Requires-Dist: coverage ; extra == 'test'
Requires-Dist: cryptography ; extra == 'test'
Requires-Dist: jsonschema ; extra == 'test'
Requires-Dist: jupyterlab >=3 ; extra == 'test'
Requires-Dist: mock ; extra == 'test'
Requires-Dist: nbclassic ; extra == 'test'
Requires-Dist: pytest <8,>=3.3 ; extra == 'test'
Requires-Dist: pytest-asyncio <0.23,>=0.17 ; extra == 'test'
Requires-Dist: pytest-cov ; extra == 'test'
Requires-Dist: requests-mock ; extra == 'test'
Requires-Dist: playwright ; extra == 'test'
Requires-Dist: pytest-rerunfailures ; extra == 'test'
Requires-Dist: virtualenv ; extra == 'test'
